[
  [
    {
      "symbol": "",
      "clickable": true
    },
    {
      "symbol": "",
      "clickable": true
    },
    {
      "symbol": "",
      "clickable": true 
    },
    {
      "symbol": "",
      "clickable": true
    }
  ],
  [
    {
      "symbol": "",
      "clickable": true
    },
    {
      "symbol": "",
      "clickable": true
    },
    {
      "symbol": "",
      "clickable": true
    },
    {
      "symbol": "",
      "clickable": true
    }
  ],
  [
    {
      "symbol": "",
      "clickable": true
    },
    {
      "symbol": "",
      "clickable": true
    },
    {
      "symbol": "",
      "clickable": true
    },
    {
      "symbol": "",
      "clickable": true
    }
  ],
  []
    {
      "symbol": "",
      "clickable": true
    },
    {
      "symbol": "",
      "clickable": true
    },
    {
      "symbol": "",
      "clickable": true
    },
    {
      "symbol": "",
      "clickable": true
    }
]
